README.md
pyproject.toml
setup.cfg
setup.py
hedera_api.egg-info/PKG-INFO
hedera_api.egg-info/SOURCES.txt
hedera_api.egg-info/dependency_links.txt
hedera_api.egg-info/requires.txt
hedera_api.egg-info/top_level.txt
hedera_api_client/__init__.py
hedera_api_client/api_client.py
hedera_api_client/api_response.py
hedera_api_client/configuration.py
hedera_api_client/exceptions.py
hedera_api_client/py.typed
hedera_api_client/rest.py
hedera_api_client/api/__init__.py
hedera_api_client/api/access_api.py
hedera_api_client/api/access_iiif_refresh_api.py
hedera_api_client/api/access_projects_api.py
hedera_api_client/api/access_research_objects_api.py
hedera_api_client/api/admin_api.py
hedera_api_client/api/admin_application_roles_api.py
hedera_api_client/api/admin_authorized_projects_api.py
hedera_api_client/api/admin_funding_agencies_api.py
hedera_api_client/api/admin_global_banners_api.py
hedera_api_client/api/admin_iiif_collection_configs_api.py
hedera_api_client/api/admin_institutions_api.py
hedera_api_client/api/admin_languages_api.py
hedera_api_client/api/admin_licenses_api.py
hedera_api_client/api/admin_modules_api.py
hedera_api_client/api/admin_monitor_api.py
hedera_api_client/api/admin_ontologies_api.py
hedera_api_client/api/admin_people_api.py
hedera_api_client/api/admin_projects_api.py
hedera_api_client/api/admin_research_object_types_api.py
hedera_api_client/api/admin_rmls_api.py
hedera_api_client/api/admin_roles_api.py
hedera_api_client/api/admin_sparql_saved_queries_api.py
hedera_api_client/api/admin_system_properties_api.py
hedera_api_client/api/admin_triplestore_api.py
hedera_api_client/api/admin_triplestore_datasets_api.py
hedera_api_client/api/admin_users_api.py
hedera_api_client/api/current_configuration_api.py
hedera_api_client/api/default_configuration_api.py
hedera_api_client/api/hedera_api.py
hedera_api_client/api/iiif_collections_api.py
hedera_api_client/api/iiif_images_cookie_api.py
hedera_api_client/api/iiif_manifest_cookie_api.py
hedera_api_client/api/iiif_manifests_api.py
hedera_api_client/api/iiif_protocol_version_api.py
hedera_api_client/api/index_api.py
hedera_api_client/api/index_index_field_aliases_api.py
