Metadata-Version: 2.4
Name: hedera-api
Version: 1.2.1
Summary: hedera Solution API
Home-page: 
Author: University of Geneva
Author-email: eresearch-opensource@unige.ch
License: GNU General Public License v2.0 or later
Keywords: OpenAPI,OpenAPI-Generator,hedera Solution API
Requires-Dist: urllib3<3.0.0,>=1.25.3
Requires-Dist: python-dateutil>=2.8.2
Requires-Dist: pydantic>=2
Requires-Dist: typing-extensions>=4.7.1
Dynamic: author
Dynamic: author-email
Dynamic: description
Dynamic: description-content-type
Dynamic: keywords
Dynamic: license
Dynamic: requires-dist
Dynamic: summary
